MANIFEST.in
README.rst
setup.py
pyramid_recipe_modwsgi/__init__.py
pyramid_recipe_modwsgi.egg-info/PKG-INFO
pyramid_recipe_modwsgi.egg-info/SOURCES.txt
pyramid_recipe_modwsgi.egg-info/dependency_links.txt
pyramid_recipe_modwsgi.egg-info/entry_points.txt
pyramid_recipe_modwsgi.egg-info/not-zip-safe
pyramid_recipe_modwsgi.egg-info/requires.txt
pyramid_recipe_modwsgi.egg-info/top_level.txt