Metadata-Version: 1.1
Name: pyramid-recipe-modwsgi
Version: 0.1
Summary: zc.buildout recipe to create apache modwsgi file.
Home-page: https://github.com/garbas/pyramid_recipe_modwsgi
Author: Rok Garbas
Author-email: rok@garbas.si
License: MIT
Keywords: apache pyramid wsgi buildout
Platform: UNKNOWN
Classifier: Development Status :: 5 - Production/Stable
Classifier: Framework :: Buildout :: Recipe
Classifier: Intended Audience :: Developers
Classifier: Intended Audience :: System Administrators
Classifier: License :: OSI Approved :: Zope Public License
Classifier: Programming Language :: Python :: 2
Classifier: Programming Language :: Python :: 2.4
Classifier: Programming Language :: Python :: 2.5
Classifier: Programming Language :: Python :: 2.6
Classifier: Programming Language :: Python :: 2.7
